psfmodel/__init__.py
psfmodel/_version.py
psfmodel/gaussian.py
psfmodel/hst.py
psfmodel/psf.py
psfmodel/py.typed
rms_psfmodel-0.0.2.dist-info/licenses/LICENSE
rms_psfmodel-0.0.2.dist-info/METADATA
rms_psfmodel-0.0.2.dist-info/WHEEL
rms_psfmodel-0.0.2.dist-info/top_level.txt
rms_psfmodel-0.0.2.dist-info/RECORD
